README.txt
setup.py
src/OpenOPC.py
src/OpenOPC_Python3x.egg-info/PKG-INFO
src/OpenOPC_Python3x.egg-info/SOURCES.txt
src/OpenOPC_Python3x.egg-info/dependency_links.txt
src/OpenOPC_Python3x.egg-info/requires.txt
src/OpenOPC_Python3x.egg-info/top_level.txt